primer/__init__.py
primer/debug.py
primer/performance.py
primer/profile.py
primer_kit-0.1.1a0.dist-info/LICENSE
primer_kit-0.1.1a0.dist-info/METADATA
primer_kit-0.1.1a0.dist-info/WHEEL
primer_kit-0.1.1a0.dist-info/top_level.txt
primer_kit-0.1.1a0.dist-info/RECORD
