Metadata-Version: 2.1
Name: primer-kit
Version: 0.1.1a0
Summary: Primer is a lightweight toolbox for debugging and benchmarking Python code.
Home-page: UNKNOWN
Author: Zhaocheng Zhu
License: MIT
Keywords: debug,benchmark
Platform: UNKNOWN
Classifier: Development Status :: 3 - Alpha
Classifier: License :: OSI Approved :: MIT License
Classifier: Programming Language :: Python :: 3
Classifier: Topic :: Software Development :: Debuggers
Classifier: Topic :: System :: Benchmark
Requires-Python: >=3.5
Requires-Dist: psutil
Requires-Dist: numpy
